MANIFEST.in
README.md
VERSION
setup.py
OMM.egg-info/PKG-INFO
OMM.egg-info/SOURCES.txt
OMM.egg-info/dependency_links.txt
OMM.egg-info/not-zip-safe
OMM.egg-info/requires.txt
OMM.egg-info/top_level.txt
omm/__init__.py
omm/fields.py
omm/helper.py
omm/model.py
omm/structures.py
tests/fields/__init__.py
tests/fields/argument_accept.py
tests/fields/casting.py
tests/fields/normal_map.py
tests/integration/__init__.py
tests/integration/mapfield/__init__.py
tests/integration/mapfield/casting.py
tests/integration/mapfield/descriptor.py
tests/integration/mapper/__init__.py
tests/integration/mapper/errors.py
tests/integration/mapper/exlude.py
tests/integration/mapper/transform_dict.py
tests/integration/mapper/transform_json.py
tests/mapper/__init__.py
tests/mapper/attr.py
tests/mapper/connectivity.py
tests/mapper/dumps_loads.py
tests/mapper/errors.py
tests/mapper/meta.py
tests/mapper/transform_dict.py
tests/mapper/transform_json.py
tests/structure/__init__.py
tests/structure/connection_dict.py