Metadata-Version: 2.1
Name: OMM
Version: 1.0.1
Summary: Object Model Mapper for Python-based web apps and/or APIs
Home-page: https://github.com/hiroaki-yamamoto/omm.git
Author: Hiroaki Yamamoto
Author-email: hiroaki@hysoftware.net
License: MIT
Keywords: json OMM Object Model Mapper Relational Document
Platform: UNKNOWN
Classifier: Programming Language :: Python :: 2
Classifier: Programming Language :: Python :: 3
